{
    "cols": [
        {
            "label": "State",
            "type": "string"
        },
        {
            "label": "Average Income",
            "type": "number"
        }
    ],
    "rows": [
        {
            "c": [
                {
                    "v": "Alabama"
                },
                {
                    "v": 31847.0461782
                }
            ]
        },
        {
            "c": [
                {
                    "v": "Alaska"
                },
                {
                    "v": 35893.8110826
                }
            ]
        },
        {
            "c": [
                {
                    "v": "Arizona"
                },
                {
                    "v": 35631.0269638
                }
            ]
        },
        {
            "c": [
                {
                    "v": "Arkansas"
                },
                {
                    "v": 28917.2267367
                }
            ]
        },
        {
            "c": [
                {
                    "v": "California"
                },
                {
                    "v": 43052.5254669
                }
            ]
        },
        {
            "c": [
                {
                    "v": "Colorado"
                },
                {
                    "v": 41228.95657
                }
            ]
        },
        {
            "c": [
                {
                    "v": "Connecticut"
                },
                {
                    "v": 51161.6364309
                }
            ]
        },
        {
            "c": [
                {
                    "v": "Delaware"
                },
                {
                    "v": 40521.9323752
                }
            ]
        },
        {
            "c": [
                {
                    "v": "District Of Columbia"
                },
                {
                    "v": 59042.0789087
                }
            ]
        },
        {
            "c": [
                {
                    "v": "Florida"
                },
                {
                    "v": 37148.6798253
                }
            ]
        },
        {
            "c": [
                {
                    "v": "Georgia"
                },
                {
                    "v": 35169.5483249
                }
            ]
        },
        {
            "c": [
                {
                    "v": "Hawaii"
                },
                {
                    "v": 38346.1766312
                }
            ]
        },
        {
            "c": [
                {
                    "v": "Idaho"
                },
                {
                    "v": 30759.7403899
                }
            ]
        },
        {
            "c": [
                {
                    "v": "Illinois"
                },
                {
                    "v": 39555.4246516
                }
            ]
        },
        {
            "c": [
                {
                    "v": "Indiana"
                },
                {
                    "v": 32374.3326647
                }
            ]
        },
        {
            "c": [
                {
                    "v": "Iowa"
                },
                {
                    "v": 32975.0948134
                }
            ]
        },
        {
            "c": [
                {
                    "v": "Kansas"
                },
                {
                    "v": 34223.7187904
                }
            ]
        },
        {
            "c": [
                {
                    "v": "Kentucky"
                },
                {
                    "v": 31368.9259667
                }
            ]
        },
        {
            "c": [
                {
                    "v": "Louisiana"
                },
                {
                    "v": 33442.5965305
                }
            ]
        },
        {
            "c": [
                {
                    "v": "Maine"
                },
                {
                    "v": 31306.0364334
                }
            ]
        },
        {
            "c": [
                {
                    "v": "Maryland"
                },
                {
                    "v": 49451.5914346
                }
            ]
        },
        {
            "c": [
                {
                    "v": "Massachusetts"
                },
                {
                    "v": 45716.5264845
                }
            ]
        },
        {
            "c": [
                {
                    "v": "Michigan"
                },
                {
                    "v": 33719.7679048
                }
            ]
        },
        {
            "c": [
                {
                    "v": "Minnesota"
                },
                {
                    "v": 37755.9852158
                }
            ]
        },
        {
            "c": [
                {
                    "v": "Mississippi"
                },
                {
                    "v": 28756.5661064
                }
            ]
        },
        {
            "c": [
                {
                    "v": "Missouri"
                },
                {
                    "v": 32686.9493567
                }
            ]
        },
        {
            "c": [
                {
                    "v": "Montana"
                },
                {
                    "v": 31987.5857372
                }
            ]
        },
        {
            "c": [
                {
                    "v": "Nebraska"
                },
                {
                    "v": 34120.4092277
                }
            ]
        },
        {
            "c": [
                {
                    "v": "Nevada"
                },
                {
                    "v": 36779.8081341
                }
            ]
        },
        {
            "c": [
                {
                    "v": "New Hampshire"
                },
                {
                    "v": 41542.7210226
                }
            ]
        },
        {
            "c": [
                {
                    "v": "New Jersey"
                },
                {
                    "v": 49974.5180036
                }
            ]
        },
        {
            "c": [
                {
                    "v": "New Mexico"
                },
                {
                    "v": 34442.88757
                }
            ]
        },
        {
            "c": [
                {
                    "v": "New York"
                },
                {
                    "v": 42685.2557666
                }
            ]
        },
        {
            "c": [
                {
                    "v": "North Carolina"
                },
                {
                    "v": 34102.3879599
                }
            ]
        },
        {
            "c": [
                {
                    "v": "North Dakota"
                },
                {
                    "v": 36191.5373972
                }
            ]
        },
        {
            "c": [
                {
                    "v": "Ohio"
                },
                {
                    "v": 33673.5484032
                }
            ]
        },
        {
            "c": [
                {
                    "v": "Oklahoma"
                },
                {
                    "v": 31948.6516922
                }
            ]
        },
        {
            "c": [
                {
                    "v": "Oregon"
                },
                {
                    "v": 35540.2543639
                }
            ]
        },
        {
            "c": [
                {
                    "v": "Pennsylvania"
                },
                {
                    "v": 35215.9479345
                }
            ]
        },
        {
            "c": [
                {
                    "v": "Rhode Island"
                },
                {
                    "v": 39566.9712275
                }
            ]
        },
        {
            "c": [
                {
                    "v": "South Carolina"
                },
                {
                    "v": 32052.5137906
                }
            ]
        },
        {
            "c": [
                {
                    "v": "South Dakota"
                },
                {
                    "v": 32095.7436875
                }
            ]
        },
        {
            "c": [
                {
                    "v": "Tennessee"
                },
                {
                    "v": 32743.446477
                }
            ]
        },
        {
            "c": [
                {
                    "v": "Texas"
                },
                {
                    "v": 38085.0036362
                }
            ]
        },
        {
            "c": [
                {
                    "v": "Utah"
                },
                {
                    "v": 36496.4571412
                }
            ]
        },
        {
            "c": [
                {
                    "v": "Vermont"
                },
                {
                    "v": 35385.1807557
                }
            ]
        },
        {
            "c": [
                {
                    "v": "Virginia"
                },
                {
                    "v": 44244.057036
                }
            ]
        },
        {
            "c": [
                {
                    "v": "Washington"
                },
                {
                    "v": 40988.9843251
                }
            ]
        },
        {
            "c": [
                {
                    "v": "West Virginia"
                },
                {
                    "v": 29617.636538
                }
            ]
        },
        {
            "c": [
                {
                    "v": "Wisconsin"
                },
                {
                    "v": 34199.4683272
                }
            ]
        },
        {
            "c": [
                {
                    "v": "Wyoming"
                },
                {
                    "v": 36420.663787
                }
            ]
        }
    ]
}